[
    {
        "coords": "77,13 77,119 960,119 960,13",
        "baseline": null,
        "text": ""
    },
    {
        "coords": "79,122 79,257 1015,262 1017,128",
        "baseline": null,
        "text": ""
    },
    {
        "coords": "1044,5 1044,123 1916,123 1916,5",
        "baseline": null,
        "text": ""
    },
    {
        "coords": "1035,122 1030,258 1980,257 1981,122",
        "baseline": null,
        "text": ""
    },
    {
        "coords": "1036,260 1037,365 1128,365 1126,260",
        "baseline": null,
        "text": ""
    },
    {
        "coords": "1126,260 1128,365 1168,365 1166,260",
        "baseline": null,
        "text": ""
    },
    {
        "coords": "1166,260 1168,365 1207,365 1205,260",
        "baseline": null,
        "text": ""
    },
    {
        "coords": "1205,260 1207,365 1526,365 1524,260",
        "baseline": null,
        "text": ""
    },
    {
        "coords": "1524,260 1526,365 1566,365 1564,260",
        "baseline": null,
        "text": ""
    },
    {
        "coords": "1564,260 1566,365 1609,365 1607,260",
        "baseline": null,
        "text": ""
    },
    {
        "coords": "1607,260 1609,365 1724,365 1722,260",
        "baseline": null,
        "text": ""
    },
    {
        "coords": "1722,260 1724,365 1766,365 1764,260",
        "baseline": null,
        "text": ""
    },
    {
        "coords": "1764,260 1766,365 1990,365 1989,259",
        "baseline": null,
        "text": ""
    },
    {
        "coords": "1037,365 1041,619 1133,619 1128,365",
        "baseline": null,
        "text": ""
    },
    {
        "coords": "1128,365 1133,619 1173,619 1168,365",
        "baseline": null,
        "text": ""
    },
    {
        "coords": "1168,365 1173,619 1211,619 1207,365",
        "baseline": null,
        "text": ""
    },
    {
        "coords": "1207,365 1211,619 1531,619 1526,365",
        "baseline": null,
        "text": ""
    },
    {
        "coords": "1526,365 1531,619 1570,619 1566,365",
        "baseline": null,
        "text": ""
    },
    {
        "coords": "1566,365 1570,619 1613,619 1609,365",
        "baseline": null,
        "text": ""
    },
    {
        "coords": "1609,365 1613,619 1728,619 1724,365",
        "baseline": null,
        "text": ""
    },
    {
        "coords": "1724,365 1728,619 1771,619 1766,365",
        "baseline": null,
        "text": ""
    },
    {
        "coords": "1766,365 1771,619 1992,619 1990,365",
        "baseline": null,
        "text": ""
    },
    {
        "coords": "1041,619 1042,665 1134,665 1133,619",
        "baseline": null,
        "text": ""
    },
    {
        "coords": "1133,619 1134,665 1174,665 1173,619",
        "baseline": null,
        "text": ""
    },
    {
        "coords": "1173,619 1174,665 1212,665 1211,619",
        "baseline": null,
        "text": ""
    },
    {
        "coords": "1211,619 1212,665 1532,665 1531,619",
        "baseline": null,
        "text": ""
    },
    {
        "coords": "1531,619 1532,665 1571,665 1570,619",
        "baseline": null,
        "text": ""
    },
    {
        "coords": "1570,619 1571,665 1614,665 1613,619",
        "baseline": null,
        "text": ""
    },
    {
        "coords": "1613,619 1614,665 1729,665 1728,619",
        "baseline": null,
        "text": ""
    },
    {
        "coords": "1728,619 1729,665 1772,665 1771,619",
        "baseline": null,
        "text": ""
    },
    {
        "coords": "1771,619 1772,665 1992,665 1992,619",
        "baseline": null,
        "text": ""
    },
    {
        "coords": "1042,665 1043,712 1135,712 1134,665",
        "baseline": null,
        "text": ""
    },
    {
        "coords": "1134,665 1135,712 1175,712 1174,665",
        "baseline": null,
        "text": ""
    },
    {
        "coords": "1174,665 1175,712 1213,712 1212,665",
        "baseline": null,
        "text": ""
    },
    {
        "coords": "1212,665 1213,712 1533,712 1532,665",
        "baseline": null,
        "text": ""
    },
    {
        "coords": "1532,665 1533,712 1572,712 1571,665",
        "baseline": null,
        "text": ""
    },
    {
        "coords": "1571,665 1572,712 1615,712 1614,665",
        "baseline": null,
        "text": ""
    },
    {
        "coords": "1614,665 1615,712 1730,712 1729,665",
        "baseline": null,
        "text": ""
    },
    {
        "coords": "1729,665 1730,712 1773,712 1772,665",
        "baseline": null,
        "text": ""
    },
    {
        "coords": "1772,665 1773,712 1992,712 1992,665",
        "baseline": null,
        "text": ""
    },
    {
        "coords": "1043,712 1044,757 1136,757 1135,712",
        "baseline": null,
        "text": ""
    },
    {
        "coords": "1135,712 1136,757 1176,757 1175,712",
        "baseline": null,
        "text": ""
    },
    {
        "coords": "1175,712 1176,757 1214,757 1213,712",
        "baseline": null,
        "text": ""
    },
    {
        "coords": "1213,712 1214,757 1534,757 1533,712",
        "baseline": null,
        "text": ""
    },
    {
        "coords": "1533,712 1534,757 1573,757 1572,712",
        "baseline": null,
        "text": ""
    },
    {
        "coords": "1572,712 1573,757 1616,757 1615,712",
        "baseline": null,
        "text": ""
    },
    {
        "coords": "1615,712 1616,757 1731,757 1730,712",
        "baseline": null,
        "text": ""
    },
    {
        "coords": "1730,712 1731,757 1774,757 1773,712",
        "baseline": null,
        "text": ""
    },
    {
        "coords": "1773,712 1774,757 1992,757 1992,712",
        "baseline": null,
        "text": ""
    },
    {
        "coords": "1044,757 1045,804 1137,804 1136,757",
        "baseline": null,
        "text": ""
    },
    {
        "coords": "1136,757 1137,804 1177,804 1176,757",
        "baseline": null,
        "text": ""
    },
    {
        "coords": "1176,757 1177,804 1215,804 1214,757",
        "baseline": null,
        "text": ""
    },
    {
        "coords": "1214,757 1215,804 1535,804 1534,757",
        "baseline": null,
        "text": ""
    },
    {
        "coords": "1534,757 1535,804 1574,804 1573,757",
        "baseline": null,
        "text": ""
    },
    {
        "coords": "1573,757 1574,804 1617,804 1616,757",
        "baseline": null,
        "text": ""
    },
    {
        "coords": "1616,757 1617,804 1732,804 1731,757",
        "baseline": null,
        "text": ""
    },
    {
        "coords": "1731,757 1732,804 1775,804 1774,757",
        "baseline": null,
        "text": ""
    },
    {
        "coords": "1774,757 1775,804 1992,804 1992,757",
        "baseline": null,
        "text": ""
    },
    {
        "coords": "1045,804 1045,844 1138,844 1137,804",
        "baseline": null,
        "text": ""
    },
    {
        "coords": "1137,804 1138,844 1178,844 1177,804",
        "baseline": null,
        "text": ""
    },
    {
        "coords": "1177,804 1178,844 1216,844 1215,804",
        "baseline": null,
        "text": ""
    },
    {
        "coords": "1215,804 1216,844 1536,844 1535,804",
        "baseline": null,
        "text": ""
    },
    {
        "coords": "1535,804 1536,844 1575,844 1574,804",
        "baseline": null,
        "text": ""
    },
    {
        "coords": "1574,804 1575,844 1618,844 1617,804",
        "baseline": null,
        "text": ""
    },
    {
        "coords": "1617,804 1618,844 1733,844 1732,804",
        "baseline": null,
        "text": ""
    },
    {
        "coords": "1732,804 1733,844 1776,844 1775,804",
        "baseline": null,
        "text": ""
    },
    {
        "coords": "1775,804 1776,844 1992,844 1992,804",
        "baseline": null,
        "text": ""
    },
    {
        "coords": "1045,844 1046,936 1139,936 1138,844",
        "baseline": null,
        "text": ""
    },
    {
        "coords": "1138,844 1139,936 1179,936 1178,844",
        "baseline": null,
        "text": ""
    },
    {
        "coords": "1178,844 1179,936 1217,936 1216,844",
        "baseline": null,
        "text": ""
    },
    {
        "coords": "1216,844 1217,936 1537,936 1536,844",
        "baseline": null,
        "text": ""
    },
    {
        "coords": "1536,844 1537,936 1576,936 1575,844",
        "baseline": null,
        "text": ""
    },
    {
        "coords": "1575,844 1576,936 1619,936 1618,844",
        "baseline": null,
        "text": ""
    },
    {
        "coords": "1618,844 1619,936 1734,936 1733,844",
        "baseline": null,
        "text": ""
    },
    {
        "coords": "1733,844 1734,936 1777,936 1776,844",
        "baseline": null,
        "text": ""
    },
    {
        "coords": "1776,844 1777,936 1993,936 1992,844",
        "baseline": null,
        "text": ""
    },
    {
        "coords": "1046,936 1047,982 1140,982 1139,936",
        "baseline": null,
        "text": ""
    },
    {
        "coords": "1139,936 1140,982 1180,982 1179,936",
        "baseline": null,
        "text": ""
    },
    {
        "coords": "1179,936 1180,982 1218,982 1217,936",
        "baseline": null,
        "text": ""
    },
    {
        "coords": "1217,936 1218,982 1538,982 1537,936",
        "baseline": null,
        "text": ""
    },
    {
        "coords": "1537,936 1538,982 1577,982 1576,936",
        "baseline": null,
        "text": ""
    },
    {
        "coords": "1576,936 1577,982 1620,982 1619,936",
        "baseline": null,
        "text": ""
    },
    {
        "coords": "1619,936 1620,982 1735,982 1734,936",
        "baseline": null,
        "text": ""
    },
    {
        "coords": "1734,936 1735,982 1778,982 1777,936",
        "baseline": null,
        "text": ""
    },
    {
        "coords": "1777,936 1778,982 1993,982 1993,936",
        "baseline": null,
        "text": ""
    },
    {
        "coords": "1047,982 1048,1027 1141,1027 1140,982",
        "baseline": null,
        "text": ""
    },
    {
        "coords": "1140,982 1141,1027 1181,1027 1180,982",
        "baseline": null,
        "text": ""
    },
    {
        "coords": "1180,982 1181,1027 1219,1027 1218,982",
        "baseline": null,
        "text": ""
    },
    {
        "coords": "1218,982 1219,1027 1539,1027 1538,982",
        "baseline": null,
        "text": ""
    },
    {
        "coords": "1538,982 1539,1027 1578,1027 1577,982",
        "baseline": null,
        "text": ""
    },
    {
        "coords": "1577,982 1578,1027 1621,1027 1620,982",
        "baseline": null,
        "text": ""
    },
    {
        "coords": "1620,982 1621,1027 1736,1027 1735,982",
        "baseline": null,
        "text": ""
    },
    {
        "coords": "1735,982 1736,1027 1779,1027 1778,982",
        "baseline": null,
        "text": ""
    },
    {
        "coords": "1778,982 1779,1027 1993,1027 1993,982",
        "baseline": null,
        "text": ""
    },
    {
        "coords": "1048,1027 1048,1064 1142,1064 1141,1027",
        "baseline": null,
        "text": ""
    },
    {
        "coords": "1141,1027 1142,1064 1182,1064 1181,1027",
        "baseline": null,
        "text": ""
    },
    {
        "coords": "1181,1027 1182,1064 1220,1064 1219,1027",
        "baseline": null,
        "text": ""
    },
    {
        "coords": "1219,1027 1220,1064 1540,1064 1539,1027",
        "baseline": null,
        "text": ""
    },
    {
        "coords": "1539,1027 1540,1064 1579,1064 1578,1027",
        "baseline": null,
        "text": ""
    },
    {
        "coords": "1578,1027 1579,1064 1622,1064 1621,1027",
        "baseline": null,
        "text": ""
    },
    {
        "coords": "1621,1027 1622,1064 1737,1064 1736,1027",
        "baseline": null,
        "text": ""
    },
    {
        "coords": "1736,1027 1737,1064 1780,1064 1779,1027",
        "baseline": null,
        "text": ""
    },
    {
        "coords": "1779,1027 1780,1064 1993,1064 1993,1027",
        "baseline": null,
        "text": ""
    },
    {
        "coords": "1048,1064 1049,1108 1143,1108 1142,1064",
        "baseline": null,
        "text": ""
    },
    {
        "coords": "1142,1064 1143,1108 1183,1108 1182,1064",
        "baseline": null,
        "text": ""
    },
    {
        "coords": "1182,1064 1183,1108 1221,1108 1220,1064",
        "baseline": null,
        "text": ""
    },
    {
        "coords": "1220,1064 1221,1108 1541,1108 1540,1064",
        "baseline": null,
        "text": ""
    },
    {
        "coords": "1540,1064 1541,1108 1580,1108 1579,1064",
        "baseline": null,
        "text": ""
    },
    {
        "coords": "1579,1064 1580,1108 1623,1108 1622,1064",
        "baseline": null,
        "text": ""
    },
    {
        "coords": "1622,1064 1623,1108 1738,1108 1737,1064",
        "baseline": null,
        "text": ""
    },
    {
        "coords": "1737,1064 1738,1108 1781,1108 1780,1064",
        "baseline": null,
        "text": ""
    },
    {
        "coords": "1780,1064 1781,1108 1993,1108 1993,1064",
        "baseline": null,
        "text": ""
    },
    {
        "coords": "1049,1108 1050,1195 1144,1195 1143,1108",
        "baseline": null,
        "text": ""
    },
    {
        "coords": "1143,1108 1144,1195 1184,1195 1183,1108",
        "baseline": null,
        "text": ""
    },
    {
        "coords": "1183,1108 1184,1195 1222,1195 1221,1108",
        "baseline": null,
        "text": ""
    },
    {
        "coords": "1221,1108 1222,1195 1542,1195 1541,1108",
        "baseline": null,
        "text": ""
    },
    {
        "coords": "1541,1108 1542,1195 1581,1195 1580,1108",
        "baseline": null,
        "text": ""
    },
    {
        "coords": "1580,1108 1581,1195 1624,1195 1623,1108",
        "baseline": null,
        "text": ""
    },
    {
        "coords": "1623,1108 1624,1195 1739,1195 1738,1108",
        "baseline": null,
        "text": ""
    },
    {
        "coords": "1738,1108 1739,1195 1782,1195 1781,1108",
        "baseline": null,
        "text": ""
    },
    {
        "coords": "1781,1108 1782,1195 1994,1195 1993,1108",
        "baseline": null,
        "text": ""
    },
    {
        "coords": "1050,1195 1051,1245 1145,1245 1144,1195",
        "baseline": null,
        "text": ""
    },
    {
        "coords": "1144,1195 1145,1245 1185,1245 1184,1195",
        "baseline": null,
        "text": ""
    },
    {
        "coords": "1184,1195 1185,1245 1223,1245 1222,1195",
        "baseline": null,
        "text": ""
    },
    {
        "coords": "1222,1195 1223,1245 1543,1245 1542,1195",
        "baseline": null,
        "text": ""
    },
    {
        "coords": "1542,1195 1543,1245 1582,1245 1581,1195",
        "baseline": null,
        "text": ""
    },
    {
        "coords": "1581,1195 1582,1245 1625,1245 1624,1195",
        "baseline": null,
        "text": ""
    },
    {
        "coords": "1624,1195 1625,1245 1740,1245 1739,1195",
        "baseline": null,
        "text": ""
    },
    {
        "coords": "1739,1195 1740,1245 1783,1245 1782,1195",
        "baseline": null,
        "text": ""
    },
    {
        "coords": "1782,1195 1783,1245 1995,1245 1994,1195",
        "baseline": null,
        "text": ""
    },
    {
        "coords": "1051,1245 1052,1375 1147,1375 1145,1245",
        "baseline": null,
        "text": ""
    },
    {
        "coords": "1145,1245 1147,1375 1187,1375 1185,1245",
        "baseline": null,
        "text": ""
    },
    {
        "coords": "1185,1245 1187,1375 1225,1375 1223,1245",
        "baseline": null,
        "text": ""
    },
    {
        "coords": "1223,1245 1225,1375 1545,1375 1543,1245",
        "baseline": null,
        "text": ""
    },
    {
        "coords": "1543,1245 1545,1375 1584,1375 1582,1245",
        "baseline": null,
        "text": ""
    },
    {
        "coords": "1582,1245 1584,1375 1627,1375 1625,1245",
        "baseline": null,
        "text": ""
    },
    {
        "coords": "1625,1245 1627,1375 1742,1375 1740,1245",
        "baseline": null,
        "text": ""
    },
    {
        "coords": "1740,1245 1742,1375 1785,1375 1783,1245",
        "baseline": null,
        "text": ""
    },
    {
        "coords": "1783,1245 1785,1375 1996,1375 1995,1245",
        "baseline": null,
        "text": ""
    },
    {
        "coords": "1052,1375 1052,1424 1147,1424 1147,1375",
        "baseline": null,
        "text": ""
    },
    {
        "coords": "1147,1375 1147,1424 1187,1424 1187,1375",
        "baseline": null,
        "text": ""
    },
    {
        "coords": "1187,1375 1187,1424 1225,1424 1225,1375",
        "baseline": null,
        "text": ""
    },
    {
        "coords": "1225,1375 1225,1424 1545,1424 1545,1375",
        "baseline": null,
        "text": ""
    },
    {
        "coords": "1545,1375 1545,1424 1584,1424 1584,1375",
        "baseline": null,
        "text": ""
    },
    {
        "coords": "1584,1375 1584,1424 1627,1424 1627,1375",
        "baseline": null,
        "text": ""
    },
    {
        "coords": "1627,1375 1627,1424 1742,1424 1742,1375",
        "baseline": null,
        "text": ""
    },
    {
        "coords": "1742,1375 1742,1424 1785,1424 1785,1375",
        "baseline": null,
        "text": ""
    },
    {
        "coords": "1785,1375 1785,1424 1996,1424 1996,1375",
        "baseline": null,
        "text": ""
    },
    {
        "coords": "1052,1424 1053,1490 1148,1489 1147,1424",
        "baseline": null,
        "text": ""
    },
    {
        "coords": "1147,1424 1148,1489 1188,1489 1187,1424",
        "baseline": null,
        "text": ""
    },
    {
        "coords": "1187,1424 1188,1489 1226,1489 1225,1424",
        "baseline": null,
        "text": ""
    },
    {
        "coords": "1225,1424 1226,1489 1546,1487 1545,1424",
        "baseline": null,
        "text": ""
    },
    {
        "coords": "1545,1424 1546,1487 1585,1487 1584,1424",
        "baseline": null,
        "text": ""
    },
    {
        "coords": "1584,1424 1585,1487 1628,1487 1627,1424",
        "baseline": null,
        "text": ""
    },
    {
        "coords": "1627,1424 1628,1487 1743,1486 1742,1424",
        "baseline": null,
        "text": ""
    },
    {
        "coords": "1742,1424 1743,1486 1786,1486 1785,1424",
        "baseline": null,
        "text": ""
    },
    {
        "coords": "1785,1424 1786,1486 1997,1484 1996,1424",
        "baseline": null,
        "text": ""
    },
    {
        "coords": "78,255 77,372 167,372 169,255",
        "baseline": null,
        "text": ""
    },
    {
        "coords": "169,255 167,372 211,372 213,255",
        "baseline": null,
        "text": ""
    },
    {
        "coords": "213,255 211,372 248,372 250,255",
        "baseline": null,
        "text": ""
    },
    {
        "coords": "250,255 248,372 565,372 567,256",
        "baseline": null,
        "text": ""
    },
    {
        "coords": "567,256 565,372 602,372 604,256",
        "baseline": null,
        "text": ""
    },
    {
        "coords": "604,256 602,372 648,372 650,256",
        "baseline": null,
        "text": ""
    },
    {
        "coords": "650,256 648,372 766,372 768,256",
        "baseline": null,
        "text": ""
    },
    {
        "coords": "768,256 766,372 808,372 810,256",
        "baseline": null,
        "text": ""
    },
    {
        "coords": "810,256 808,372 1014,372 1016,257",
        "baseline": null,
        "text": ""
    },
    {
        "coords": "77,372 76,487 165,487 167,372",
        "baseline": null,
        "text": ""
    },
    {
        "coords": "167,372 165,487 209,487 211,372",
        "baseline": null,
        "text": ""
    },
    {
        "coords": "211,372 209,487 246,487 248,372",
        "baseline": null,
        "text": ""
    },
    {
        "coords": "248,372 246,487 563,487 565,372",
        "baseline": null,
        "text": ""
    },
    {
        "coords": "565,372 563,487 600,487 602,372",
        "baseline": null,
        "text": ""
    },
    {
        "coords": "602,372 600,487 646,487 648,372",
        "baseline": null,
        "text": ""
    },
    {
        "coords": "648,372 646,487 764,487 766,372",
        "baseline": null,
        "text": ""
    },
    {
        "coords": "766,372 764,487 806,487 808,372",
        "baseline": null,
        "text": ""
    },
    {
        "coords": "808,372 806,487 1012,487 1014,372",
        "baseline": null,
        "text": ""
    },
    {
        "coords": "76,487 75,577 163,577 165,487",
        "baseline": null,
        "text": ""
    },
    {
        "coords": "165,487 163,577 207,577 209,487",
        "baseline": null,
        "text": ""
    },
    {
        "coords": "209,487 207,577 244,577 246,487",
        "baseline": null,
        "text": ""
    },
    {
        "coords": "246,487 244,577 561,577 563,487",
        "baseline": null,
        "text": ""
    },
    {
        "coords": "563,487 561,577 598,577 600,487",
        "baseline": null,
        "text": ""
    },
    {
        "coords": "600,487 598,577 644,577 646,487",
        "baseline": null,
        "text": ""
    },
    {
        "coords": "646,487 644,577 762,577 764,487",
        "baseline": null,
        "text": ""
    },
    {
        "coords": "764,487 762,577 804,577 806,487",
        "baseline": null,
        "text": ""
    },
    {
        "coords": "806,487 804,577 1010,577 1012,487",
        "baseline": null,
        "text": ""
    },
    {
        "coords": "75,577 74,624 162,624 163,577",
        "baseline": null,
        "text": ""
    },
    {
        "coords": "163,577 162,624 206,624 207,577",
        "baseline": null,
        "text": ""
    },
    {
        "coords": "207,577 206,624 243,624 244,577",
        "baseline": null,
        "text": ""
    },
    {
        "coords": "244,577 243,624 560,624 561,577",
        "baseline": null,
        "text": ""
    },
    {
        "coords": "561,577 560,624 597,624 598,577",
        "baseline": null,
        "text": ""
    },
    {
        "coords": "598,577 597,624 643,624 644,577",
        "baseline": null,
        "text": ""
    },
    {
        "coords": "644,577 643,624 761,624 762,577",
        "baseline": null,
        "text": ""
    },
    {
        "coords": "762,577 761,624 803,624 804,577",
        "baseline": null,
        "text": ""
    },
    {
        "coords": "804,577 803,624 1009,624 1010,577",
        "baseline": null,
        "text": ""
    },
    {
        "coords": "74,624 74,664 161,664 162,624",
        "baseline": null,
        "text": ""
    },
    {
        "coords": "162,624 161,664 205,664 206,624",
        "baseline": null,
        "text": ""
    },
    {
        "coords": "206,624 205,664 242,664 243,624",
        "baseline": null,
        "text": ""
    },
    {
        "coords": "243,624 242,664 559,664 560,624",
        "baseline": null,
        "text": ""
    },
    {
        "coords": "560,624 559,664 596,664 597,624",
        "baseline": null,
        "text": ""
    },
    {
        "coords": "597,624 596,664 642,664 643,624",
        "baseline": null,
        "text": ""
    },
    {
        "coords": "643,624 642,664 760,664 761,624",
        "baseline": null,
        "text": ""
    },
    {
        "coords": "761,624 760,664 802,664 803,624",
        "baseline": null,
        "text": ""
    },
    {
        "coords": "803,624 802,664 1008,664 1009,624",
        "baseline": null,
        "text": ""
    },
    {
        "coords": "74,664 73,706 160,706 161,664",
        "baseline": null,
        "text": ""
    },
    {
        "coords": "161,664 160,706 204,706 205,664",
        "baseline": null,
        "text": ""
    },
    {
        "coords": "205,664 204,706 241,706 242,664",
        "baseline": null,
        "text": ""
    },
    {
        "coords": "242,664 241,706 558,706 559,664",
        "baseline": null,
        "text": ""
    },
    {
        "coords": "559,664 558,706 595,706 596,664",
        "baseline": null,
        "text": ""
    },
    {
        "coords": "596,664 595,706 641,706 642,664",
        "baseline": null,
        "text": ""
    },
    {
        "coords": "642,664 641,706 759,706 760,664",
        "baseline": null,
        "text": ""
    },
    {
        "coords": "760,664 759,706 801,706 802,664",
        "baseline": null,
        "text": ""
    },
    {
        "coords": "802,664 801,706 1007,706 1008,664",
        "baseline": null,
        "text": ""
    },
    {
        "coords": "73,706 72,756 159,756 160,706",
        "baseline": null,
        "text": ""
    },
    {
        "coords": "160,706 159,756 203,756 204,706",
        "baseline": null,
        "text": ""
    },
    {
        "coords": "204,706 203,756 240,756 241,706",
        "baseline": null,
        "text": ""
    },
    {
        "coords": "241,706 240,756 557,756 558,706",
        "baseline": null,
        "text": ""
    },
    {
        "coords": "558,706 557,756 594,756 595,706",
        "baseline": null,
        "text": ""
    },
    {
        "coords": "595,706 594,756 640,756 641,706",
        "baseline": null,
        "text": ""
    },
    {
        "coords": "641,706 640,756 758,756 759,706",
        "baseline": null,
        "text": ""
    },
    {
        "coords": "759,706 758,756 800,756 801,706",
        "baseline": null,
        "text": ""
    },
    {
        "coords": "801,706 800,756 1006,756 1007,706",
        "baseline": null,
        "text": ""
    },
    {
        "coords": "72,756 72,795 158,795 159,756",
        "baseline": null,
        "text": ""
    },
    {
        "coords": "159,756 158,795 202,795 203,756",
        "baseline": null,
        "text": ""
    },
    {
        "coords": "203,756 202,795 239,795 240,756",
        "baseline": null,
        "text": ""
    },
    {
        "coords": "240,756 239,795 556,795 557,756",
        "baseline": null,
        "text": ""
    },
    {
        "coords": "557,756 556,795 593,795 594,756",
        "baseline": null,
        "text": ""
    },
    {
        "coords": "594,756 593,795 639,795 640,756",
        "baseline": null,
        "text": ""
    },
    {
        "coords": "640,756 639,795 757,795 758,756",
        "baseline": null,
        "text": ""
    },
    {
        "coords": "758,756 757,795 799,795 800,756",
        "baseline": null,
        "text": ""
    },
    {
        "coords": "800,756 799,795 1005,795 1006,756",
        "baseline": null,
        "text": ""
    },
    {
        "coords": "72,795 71,876 157,876 158,795",
        "baseline": null,
        "text": ""
    },
    {
        "coords": "158,795 157,876 201,876 202,795",
        "baseline": null,
        "text": ""
    },
    {
        "coords": "202,795 201,876 238,876 239,795",
        "baseline": null,
        "text": ""
    },
    {
        "coords": "239,795 238,876 555,876 556,795",
        "baseline": null,
        "text": ""
    },
    {
        "coords": "556,795 555,876 592,876 593,795",
        "baseline": null,
        "text": ""
    },
    {
        "coords": "593,795 592,876 638,876 639,795",
        "baseline": null,
        "text": ""
    },
    {
        "coords": "639,795 638,876 756,876 757,795",
        "baseline": null,
        "text": ""
    },
    {
        "coords": "757,795 756,876 798,876 799,795",
        "baseline": null,
        "text": ""
    },
    {
        "coords": "799,795 798,876 1004,876 1005,795",
        "baseline": null,
        "text": ""
    },
    {
        "coords": "71,876 70,972 156,973 157,876",
        "baseline": null,
        "text": ""
    },
    {
        "coords": "157,876 156,973 199,974 201,876",
        "baseline": null,
        "text": ""
    },
    {
        "coords": "201,876 199,974 236,975 238,876",
        "baseline": null,
        "text": ""
    },
    {
        "coords": "238,876 236,975 553,980 555,876",
        "baseline": null,
        "text": ""
    },
    {
        "coords": "555,876 553,980 590,981 592,876",
        "baseline": null,
        "text": ""
    },
    {
        "coords": "592,876 590,981 636,982 638,876",
        "baseline": null,
        "text": ""
    },
    {
        "coords": "638,876 636,982 754,984 756,876",
        "baseline": null,
        "text": ""
    },
    {
        "coords": "756,876 754,984 796,984 798,876",
        "baseline": null,
        "text": ""
    },
    {
        "coords": "798,876 796,984 1002,988 1004,876",
        "baseline": null,
        "text": ""
    },
    {
        "coords": "70,972 69,1050 155,1052 156,973",
        "baseline": null,
        "text": ""
    },
    {
        "coords": "156,973 155,1052 198,1052 199,974",
        "baseline": null,
        "text": ""
    },
    {
        "coords": "199,974 198,1052 235,1053 236,975",
        "baseline": null,
        "text": ""
    },
    {
        "coords": "236,975 235,1053 552,1058 553,980",
        "baseline": null,
        "text": ""
    },
    {
        "coords": "553,980 552,1058 589,1059 590,981",
        "baseline": null,
        "text": ""
    },
    {
        "coords": "590,981 589,1059 635,1060 636,982",
        "baseline": null,
        "text": ""
    },
    {
        "coords": "636,982 635,1060 753,1062 754,984",
        "baseline": null,
        "text": ""
    },
    {
        "coords": "754,984 753,1062 795,1063 796,984",
        "baseline": null,
        "text": ""
    },
    {
        "coords": "796,984 795,1063 1001,1066 1002,988",
        "baseline": null,
        "text": ""
    },
    {
        "coords": "69,1050 68,1097 154,1098 155,1052",
        "baseline": null,
        "text": ""
    },
    {
        "coords": "155,1052 154,1098 197,1099 198,1052",
        "baseline": null,
        "text": ""
    },
    {
        "coords": "198,1052 197,1099 234,1100 235,1053",
        "baseline": null,
        "text": ""
    },
    {
        "coords": "235,1053 234,1100 551,1105 552,1058",
        "baseline": null,
        "text": ""
    },
    {
        "coords": "552,1058 551,1105 588,1106 589,1059",
        "baseline": null,
        "text": ""
    },
    {
        "coords": "589,1059 588,1106 634,1107 635,1060",
        "baseline": null,
        "text": ""
    },
    {
        "coords": "635,1060 634,1107 752,1109 753,1062",
        "baseline": null,
        "text": ""
    },
    {
        "coords": "753,1062 752,1109 794,1109 795,1063",
        "baseline": null,
        "text": ""
    },
    {
        "coords": "795,1063 794,1109 1000,1113 1001,1066",
        "baseline": null,
        "text": ""
    },
    {
        "coords": "68,1097 67,1185 153,1187 154,1098",
        "baseline": null,
        "text": ""
    },
    {
        "coords": "154,1098 153,1187 196,1188 197,1099",
        "baseline": null,
        "text": ""
    },
    {
        "coords": "197,1099 196,1188 233,1188 234,1100",
        "baseline": null,
        "text": ""
    },
    {
        "coords": "234,1100 233,1188 550,1194 551,1105",
        "baseline": null,
        "text": ""
    },
    {
        "coords": "551,1105 550,1194 587,1195 588,1106",
        "baseline": null,
        "text": ""
    },
    {
        "coords": "588,1106 587,1195 633,1195 634,1107",
        "baseline": null,
        "text": ""
    },
    {
        "coords": "634,1107 633,1195 751,1197 752,1109",
        "baseline": null,
        "text": ""
    },
    {
        "coords": "752,1109 751,1197 793,1198 794,1109",
        "baseline": null,
        "text": ""
    },
    {
        "coords": "794,1109 793,1198 999,1202 1000,1113",
        "baseline": null,
        "text": ""
    },
    {
        "coords": "67,1185 67,1229 152,1230 153,1187",
        "baseline": null,
        "text": ""
    },
    {
        "coords": "153,1187 152,1230 195,1231 196,1188",
        "baseline": null,
        "text": ""
    },
    {
        "coords": "196,1188 195,1231 232,1232 233,1188",
        "baseline": null,
        "text": ""
    },
    {
        "coords": "233,1188 232,1232 549,1237 550,1194",
        "baseline": null,
        "text": ""
    },
    {
        "coords": "550,1194 549,1237 586,1238 587,1195",
        "baseline": null,
        "text": ""
    },
    {
        "coords": "587,1195 586,1238 632,1239 633,1195",
        "baseline": null,
        "text": ""
    },
    {
        "coords": "633,1195 632,1239 750,1241 751,1197",
        "baseline": null,
        "text": ""
    },
    {
        "coords": "751,1197 750,1241 792,1242 793,1198",
        "baseline": null,
        "text": ""
    },
    {
        "coords": "793,1198 792,1242 998,1245 999,1202",
        "baseline": null,
        "text": ""
    },
    {
        "coords": "67,1229 66,1322 150,1323 152,1230",
        "baseline": null,
        "text": ""
    },
    {
        "coords": "152,1230 150,1323 193,1324 195,1231",
        "baseline": null,
        "text": ""
    },
    {
        "coords": "195,1231 193,1324 231,1324 232,1232",
        "baseline": null,
        "text": ""
    },
    {
        "coords": "232,1232 231,1324 548,1330 549,1237",
        "baseline": null,
        "text": ""
    },
    {
        "coords": "549,1237 548,1330 585,1331 586,1238",
        "baseline": null,
        "text": ""
    },
    {
        "coords": "586,1238 585,1331 631,1331 632,1239",
        "baseline": null,
        "text": ""
    },
    {
        "coords": "632,1239 631,1331 749,1333 750,1241",
        "baseline": null,
        "text": ""
    },
    {
        "coords": "750,1241 749,1333 791,1334 792,1242",
        "baseline": null,
        "text": ""
    },
    {
        "coords": "792,1242 791,1334 996,1338 998,1245",
        "baseline": null,
        "text": ""
    },
    {
        "coords": "66,1322 65,1370 149,1371 150,1323",
        "baseline": null,
        "text": ""
    },
    {
        "coords": "150,1323 149,1371 192,1372 193,1324",
        "baseline": null,
        "text": ""
    },
    {
        "coords": "193,1324 192,1372 230,1373 231,1324",
        "baseline": null,
        "text": ""
    },
    {
        "coords": "231,1324 230,1373 547,1378 548,1330",
        "baseline": null,
        "text": ""
    },
    {
        "coords": "548,1330 547,1378 584,1379 585,1331",
        "baseline": null,
        "text": ""
    },
    {
        "coords": "585,1331 584,1379 630,1380 631,1331",
        "baseline": null,
        "text": ""
    },
    {
        "coords": "631,1331 630,1380 748,1382 749,1333",
        "baseline": null,
        "text": ""
    },
    {
        "coords": "749,1333 748,1382 790,1382 791,1334",
        "baseline": null,
        "text": ""
    },
    {
        "coords": "791,1334 790,1382 995,1386 996,1338",
        "baseline": null,
        "text": ""
    },
    {
        "coords": "65,1370 65,1411 149,1412 149,1371",
        "baseline": null,
        "text": ""
    },
    {
        "coords": "149,1371 149,1412 192,1413 192,1372",
        "baseline": null,
        "text": ""
    },
    {
        "coords": "192,1372 192,1413 230,1414 230,1373",
        "baseline": null,
        "text": ""
    },
    {
        "coords": "230,1373 230,1414 547,1419 547,1378",
        "baseline": null,
        "text": ""
    },
    {
        "coords": "547,1378 547,1419 584,1420 584,1379",
        "baseline": null,
        "text": ""
    },
    {
        "coords": "584,1379 584,1420 630,1421 630,1380",
        "baseline": null,
        "text": ""
    },
    {
        "coords": "630,1380 630,1421 748,1423 748,1382",
        "baseline": null,
        "text": ""
    },
    {
        "coords": "748,1382 748,1423 790,1424 790,1382",
        "baseline": null,
        "text": ""
    },
    {
        "coords": "790,1382 790,1424 994,1427 995,1386",
        "baseline": null,
        "text": ""
    },
    {
        "coords": "65,1411 64,1466 148,1466 149,1412",
        "baseline": null,
        "text": ""
    },
    {
        "coords": "149,1412 148,1466 191,1466 192,1413",
        "baseline": null,
        "text": ""
    },
    {
        "coords": "192,1413 191,1466 229,1466 230,1414",
        "baseline": null,
        "text": ""
    },
    {
        "coords": "230,1414 229,1466 546,1467 547,1419",
        "baseline": null,
        "text": ""
    },
    {
        "coords": "547,1419 546,1467 583,1467 584,1420",
        "baseline": null,
        "text": ""
    },
    {
        "coords": "584,1420 583,1467 629,1467 630,1421",
        "baseline": null,
        "text": ""
    },
    {
        "coords": "630,1421 629,1467 747,1467 748,1423",
        "baseline": null,
        "text": ""
    },
    {
        "coords": "748,1423 747,1467 789,1467 790,1424",
        "baseline": null,
        "text": ""
    },
    {
        "coords": "790,1424 789,1467 994,1468 994,1427",
        "baseline": null,
        "text": ""
    }
]