[
    {
        "coords": "133,102 133,232 1102,232 1102,102",
        "baseline": null,
        "text": ""
    },
    {
        "coords": "142,242 142,346 1109,346 1109,242",
        "baseline": null,
        "text": ""
    },
    {
        "coords": "1137,104 1137,232 2103,232 2103,104",
        "baseline": null,
        "text": ""
    },
    {
        "coords": "1141,246 1138,343 2100,339 2100,244",
        "baseline": null,
        "text": ""
    },
    {
        "coords": "1136,345 1135,467 1184,467 1184,345",
        "baseline": null,
        "text": ""
    },
    {
        "coords": "1184,345 1184,467 1309,467 1309,344",
        "baseline": null,
        "text": ""
    },
    {
        "coords": "1309,344 1309,467 1395,467 1395,343",
        "baseline": null,
        "text": ""
    },
    {
        "coords": "1395,343 1395,467 1484,467 1484,342",
        "baseline": null,
        "text": ""
    },
    {
        "coords": "1484,342 1484,467 2011,467 2011,336",
        "baseline": null,
        "text": ""
    },
    {
        "coords": "2011,336 2011,467 2055,467 2055,336",
        "baseline": null,
        "text": ""
    },
    {
        "coords": "2055,336 2055,467 2107,467 2107,335",
        "baseline": null,
        "text": ""
    },
    {
        "coords": "1135,467 1135,552 1184,552 1184,467",
        "baseline": null,
        "text": ""
    },
    {
        "coords": "1184,467 1184,552 1309,552 1309,467",
        "baseline": null,
        "text": ""
    },
    {
        "coords": "1309,467 1309,552 1395,552 1395,467",
        "baseline": null,
        "text": ""
    },
    {
        "coords": "1395,467 1395,552 1484,552 1484,467",
        "baseline": null,
        "text": ""
    },
    {
        "coords": "1484,467 1484,552 2011,552 2011,467",
        "baseline": null,
        "text": ""
    },
    {
        "coords": "2011,467 2011,552 2055,552 2055,467",
        "baseline": null,
        "text": ""
    },
    {
        "coords": "2055,467 2055,552 2107,552 2107,467",
        "baseline": null,
        "text": ""
    },
    {
        "coords": "1135,552 1135,633 1184,633 1184,552",
        "baseline": null,
        "text": ""
    },
    {
        "coords": "1184,552 1184,633 1309,633 1309,552",
        "baseline": null,
        "text": ""
    },
    {
        "coords": "1309,552 1309,633 1395,633 1395,552",
        "baseline": null,
        "text": ""
    },
    {
        "coords": "1395,552 1395,633 1484,633 1484,552",
        "baseline": null,
        "text": ""
    },
    {
        "coords": "1484,552 1484,633 2011,633 2011,552",
        "baseline": null,
        "text": ""
    },
    {
        "coords": "2011,552 2011,633 2055,633 2055,552",
        "baseline": null,
        "text": ""
    },
    {
        "coords": "2055,552 2055,633 2107,633 2107,552",
        "baseline": null,
        "text": ""
    },
    {
        "coords": "1135,633 1135,720 1184,720 1184,633",
        "baseline": null,
        "text": ""
    },
    {
        "coords": "1184,633 1184,720 1309,720 1309,633",
        "baseline": null,
        "text": ""
    },
    {
        "coords": "1309,633 1309,720 1395,720 1395,633",
        "baseline": null,
        "text": ""
    },
    {
        "coords": "1395,633 1395,720 1484,720 1484,633",
        "baseline": null,
        "text": ""
    },
    {
        "coords": "1484,633 1484,720 2011,720 2011,633",
        "baseline": null,
        "text": ""
    },
    {
        "coords": "2011,633 2011,720 2055,720 2055,633",
        "baseline": null,
        "text": ""
    },
    {
        "coords": "2055,633 2055,720 2107,720 2107,633",
        "baseline": null,
        "text": ""
    },
    {
        "coords": "1135,720 1135,803 1184,803 1184,720",
        "baseline": null,
        "text": ""
    },
    {
        "coords": "1184,720 1184,803 1309,803 1309,720",
        "baseline": null,
        "text": ""
    },
    {
        "coords": "1309,720 1309,803 1395,803 1395,720",
        "baseline": null,
        "text": ""
    },
    {
        "coords": "1395,720 1395,803 1484,803 1484,720",
        "baseline": null,
        "text": ""
    },
    {
        "coords": "1484,720 1484,803 2011,803 2011,720",
        "baseline": null,
        "text": ""
    },
    {
        "coords": "2011,720 2011,803 2055,803 2055,720",
        "baseline": null,
        "text": ""
    },
    {
        "coords": "2055,720 2055,803 2107,803 2107,720",
        "baseline": null,
        "text": ""
    },
    {
        "coords": "1135,803 1135,882 1184,882 1184,803",
        "baseline": null,
        "text": ""
    },
    {
        "coords": "1184,803 1184,882 1309,882 1309,803",
        "baseline": null,
        "text": ""
    },
    {
        "coords": "1309,803 1309,882 1395,882 1395,803",
        "baseline": null,
        "text": ""
    },
    {
        "coords": "1395,803 1395,882 1484,882 1484,803",
        "baseline": null,
        "text": ""
    },
    {
        "coords": "1484,803 1484,882 2011,882 2011,803",
        "baseline": null,
        "text": ""
    },
    {
        "coords": "2011,803 2011,882 2055,882 2055,803",
        "baseline": null,
        "text": ""
    },
    {
        "coords": "2055,803 2055,882 2107,882 2107,803",
        "baseline": null,
        "text": ""
    },
    {
        "coords": "1135,882 1134,962 1184,962 1184,882",
        "baseline": null,
        "text": ""
    },
    {
        "coords": "1184,882 1184,962 1309,962 1309,882",
        "baseline": null,
        "text": ""
    },
    {
        "coords": "1309,882 1309,962 1395,962 1395,882",
        "baseline": null,
        "text": ""
    },
    {
        "coords": "1395,882 1395,962 1484,962 1484,882",
        "baseline": null,
        "text": ""
    },
    {
        "coords": "1484,882 1484,962 2011,962 2011,882",
        "baseline": null,
        "text": ""
    },
    {
        "coords": "2011,882 2011,962 2055,962 2055,882",
        "baseline": null,
        "text": ""
    },
    {
        "coords": "2055,882 2055,962 2107,962 2107,882",
        "baseline": null,
        "text": ""
    },
    {
        "coords": "1134,962 1134,1010 1184,1010 1184,962",
        "baseline": null,
        "text": ""
    },
    {
        "coords": "1184,962 1184,1010 1309,1010 1309,962",
        "baseline": null,
        "text": ""
    },
    {
        "coords": "1309,962 1309,1010 1395,1010 1395,962",
        "baseline": null,
        "text": ""
    },
    {
        "coords": "1395,962 1395,1010 1484,1010 1484,962",
        "baseline": null,
        "text": ""
    },
    {
        "coords": "1484,962 1484,1010 2011,1010 2011,962",
        "baseline": null,
        "text": ""
    },
    {
        "coords": "2011,962 2011,1010 2055,1010 2055,962",
        "baseline": null,
        "text": ""
    },
    {
        "coords": "2055,962 2055,1010 2107,1010 2107,962",
        "baseline": null,
        "text": ""
    },
    {
        "coords": "1134,1010 1134,1049 1184,1049 1184,1010",
        "baseline": null,
        "text": ""
    },
    {
        "coords": "1184,1010 1184,1049 1309,1049 1309,1010",
        "baseline": null,
        "text": ""
    },
    {
        "coords": "1309,1010 1309,1049 1395,1049 1395,1010",
        "baseline": null,
        "text": ""
    },
    {
        "coords": "1395,1010 1395,1049 1484,1049 1484,1010",
        "baseline": null,
        "text": ""
    },
    {
        "coords": "1484,1010 1484,1049 2011,1049 2011,1010",
        "baseline": null,
        "text": ""
    },
    {
        "coords": "2011,1010 2011,1049 2055,1049 2055,1010",
        "baseline": null,
        "text": ""
    },
    {
        "coords": "2055,1010 2055,1049 2107,1049 2107,1010",
        "baseline": null,
        "text": ""
    },
    {
        "coords": "1134,1049 1133,1125 1184,1125 1184,1049",
        "baseline": null,
        "text": ""
    },
    {
        "coords": "1184,1049 1184,1125 1309,1125 1309,1049",
        "baseline": null,
        "text": ""
    },
    {
        "coords": "1309,1049 1309,1125 1395,1125 1395,1049",
        "baseline": null,
        "text": ""
    },
    {
        "coords": "1395,1049 1395,1125 1484,1125 1484,1049",
        "baseline": null,
        "text": ""
    },
    {
        "coords": "1484,1049 1484,1125 2011,1125 2011,1049",
        "baseline": null,
        "text": ""
    },
    {
        "coords": "2011,1049 2011,1125 2055,1125 2055,1049",
        "baseline": null,
        "text": ""
    },
    {
        "coords": "2055,1049 2055,1125 2107,1125 2107,1049",
        "baseline": null,
        "text": ""
    },
    {
        "coords": "1133,1125 1133,1171 1184,1171 1184,1125",
        "baseline": null,
        "text": ""
    },
    {
        "coords": "1184,1125 1184,1171 1309,1171 1309,1125",
        "baseline": null,
        "text": ""
    },
    {
        "coords": "1309,1125 1309,1171 1395,1171 1395,1125",
        "baseline": null,
        "text": ""
    },
    {
        "coords": "1395,1125 1395,1171 1484,1171 1484,1125",
        "baseline": null,
        "text": ""
    },
    {
        "coords": "1484,1125 1484,1171 2011,1171 2011,1125",
        "baseline": null,
        "text": ""
    },
    {
        "coords": "2011,1125 2011,1171 2055,1171 2055,1125",
        "baseline": null,
        "text": ""
    },
    {
        "coords": "2055,1125 2055,1171 2107,1171 2107,1125",
        "baseline": null,
        "text": ""
    },
    {
        "coords": "1133,1171 1132,1255 1184,1255 1184,1171",
        "baseline": null,
        "text": ""
    },
    {
        "coords": "1184,1171 1184,1255 1309,1255 1309,1171",
        "baseline": null,
        "text": ""
    },
    {
        "coords": "1309,1171 1309,1255 1395,1255 1395,1171",
        "baseline": null,
        "text": ""
    },
    {
        "coords": "1395,1171 1395,1255 1484,1255 1484,1171",
        "baseline": null,
        "text": ""
    },
    {
        "coords": "1484,1171 1484,1255 2011,1255 2011,1171",
        "baseline": null,
        "text": ""
    },
    {
        "coords": "2011,1171 2011,1255 2055,1255 2055,1171",
        "baseline": null,
        "text": ""
    },
    {
        "coords": "2055,1171 2055,1255 2107,1255 2107,1171",
        "baseline": null,
        "text": ""
    },
    {
        "coords": "1132,1255 1132,1297 1184,1297 1184,1255",
        "baseline": null,
        "text": ""
    },
    {
        "coords": "1184,1255 1184,1297 1309,1297 1309,1255",
        "baseline": null,
        "text": ""
    },
    {
        "coords": "1309,1255 1309,1297 1395,1297 1395,1255",
        "baseline": null,
        "text": ""
    },
    {
        "coords": "1395,1255 1395,1297 1484,1297 1484,1255",
        "baseline": null,
        "text": ""
    },
    {
        "coords": "1484,1255 1484,1297 2011,1297 2011,1255",
        "baseline": null,
        "text": ""
    },
    {
        "coords": "2011,1255 2011,1297 2055,1297 2055,1255",
        "baseline": null,
        "text": ""
    },
    {
        "coords": "2055,1255 2055,1297 2107,1297 2107,1255",
        "baseline": null,
        "text": ""
    },
    {
        "coords": "1132,1297 1132,1336 1184,1336 1184,1297",
        "baseline": null,
        "text": ""
    },
    {
        "coords": "1184,1297 1184,1336 1309,1336 1309,1297",
        "baseline": null,
        "text": ""
    },
    {
        "coords": "1309,1297 1309,1336 1395,1336 1395,1297",
        "baseline": null,
        "text": ""
    },
    {
        "coords": "1395,1297 1395,1336 1484,1336 1484,1297",
        "baseline": null,
        "text": ""
    },
    {
        "coords": "1484,1297 1484,1336 2011,1336 2011,1297",
        "baseline": null,
        "text": ""
    },
    {
        "coords": "2011,1297 2011,1336 2055,1336 2055,1297",
        "baseline": null,
        "text": ""
    },
    {
        "coords": "2055,1297 2055,1336 2107,1336 2107,1297",
        "baseline": null,
        "text": ""
    },
    {
        "coords": "1132,1336 1131,1414 1184,1414 1184,1336",
        "baseline": null,
        "text": ""
    },
    {
        "coords": "1184,1336 1184,1414 1309,1414 1309,1336",
        "baseline": null,
        "text": ""
    },
    {
        "coords": "1309,1336 1309,1414 1395,1414 1395,1336",
        "baseline": null,
        "text": ""
    },
    {
        "coords": "1395,1336 1395,1414 1484,1414 1484,1336",
        "baseline": null,
        "text": ""
    },
    {
        "coords": "1484,1336 1484,1414 2011,1414 2011,1336",
        "baseline": null,
        "text": ""
    },
    {
        "coords": "2011,1336 2011,1414 2055,1414 2055,1336",
        "baseline": null,
        "text": ""
    },
    {
        "coords": "2055,1336 2055,1414 2107,1414 2107,1336",
        "baseline": null,
        "text": ""
    },
    {
        "coords": "1131,1414 1131,1459 1184,1459 1184,1414",
        "baseline": null,
        "text": ""
    },
    {
        "coords": "1184,1414 1184,1459 1309,1459 1309,1414",
        "baseline": null,
        "text": ""
    },
    {
        "coords": "1309,1414 1309,1459 1395,1459 1395,1414",
        "baseline": null,
        "text": ""
    },
    {
        "coords": "1395,1414 1395,1459 1484,1459 1484,1414",
        "baseline": null,
        "text": ""
    },
    {
        "coords": "1484,1414 1484,1459 2011,1459 2011,1414",
        "baseline": null,
        "text": ""
    },
    {
        "coords": "2011,1414 2011,1459 2055,1459 2055,1414",
        "baseline": null,
        "text": ""
    },
    {
        "coords": "2055,1414 2055,1459 2107,1459 2107,1414",
        "baseline": null,
        "text": ""
    },
    {
        "coords": "1131,1459 1131,1544 1184,1544 1184,1459",
        "baseline": null,
        "text": ""
    },
    {
        "coords": "1184,1459 1184,1544 1309,1544 1309,1459",
        "baseline": null,
        "text": ""
    },
    {
        "coords": "1309,1459 1309,1544 1395,1544 1395,1459",
        "baseline": null,
        "text": ""
    },
    {
        "coords": "1395,1459 1395,1544 1484,1544 1484,1459",
        "baseline": null,
        "text": ""
    },
    {
        "coords": "1484,1459 1484,1544 2011,1544 2011,1459",
        "baseline": null,
        "text": ""
    },
    {
        "coords": "2011,1459 2011,1544 2055,1544 2055,1459",
        "baseline": null,
        "text": ""
    },
    {
        "coords": "2055,1459 2055,1544 2107,1544 2107,1459",
        "baseline": null,
        "text": ""
    },
    {
        "coords": "1131,1544 1130,1644 1184,1644 1184,1544",
        "baseline": null,
        "text": ""
    },
    {
        "coords": "1184,1544 1184,1644 1309,1644 1309,1544",
        "baseline": null,
        "text": ""
    },
    {
        "coords": "1309,1544 1309,1644 1395,1644 1395,1544",
        "baseline": null,
        "text": ""
    },
    {
        "coords": "1395,1544 1395,1644 1484,1644 1484,1544",
        "baseline": null,
        "text": ""
    },
    {
        "coords": "1484,1544 1484,1644 2011,1644 2011,1544",
        "baseline": null,
        "text": ""
    },
    {
        "coords": "2011,1544 2011,1644 2055,1644 2055,1544",
        "baseline": null,
        "text": ""
    },
    {
        "coords": "2055,1544 2055,1644 2107,1644 2107,1544",
        "baseline": null,
        "text": ""
    },
    {
        "coords": "145,344 145,440 194,440 194,344",
        "baseline": null,
        "text": ""
    },
    {
        "coords": "194,344 194,440 287,440 287,343",
        "baseline": null,
        "text": ""
    },
    {
        "coords": "287,343 287,440 325,440 325,343",
        "baseline": null,
        "text": ""
    },
    {
        "coords": "325,343 325,440 379,440 379,342",
        "baseline": null,
        "text": ""
    },
    {
        "coords": "379,342 379,440 468,440 468,341",
        "baseline": null,
        "text": ""
    },
    {
        "coords": "468,341 468,440 556,440 556,340",
        "baseline": null,
        "text": ""
    },
    {
        "coords": "556,340 556,440 1024,440 1024,336",
        "baseline": null,
        "text": ""
    },
    {
        "coords": "1024,336 1024,440 1068,440 1068,336",
        "baseline": null,
        "text": ""
    },
    {
        "coords": "1068,336 1068,440 1112,440 1112,335",
        "baseline": null,
        "text": ""
    },
    {
        "coords": "145,440 145,476 194,476 194,440",
        "baseline": null,
        "text": ""
    },
    {
        "coords": "194,440 194,476 287,476 287,440",
        "baseline": null,
        "text": ""
    },
    {
        "coords": "287,440 287,476 325,476 325,440",
        "baseline": null,
        "text": ""
    },
    {
        "coords": "325,440 325,476 379,476 379,440",
        "baseline": null,
        "text": ""
    },
    {
        "coords": "379,440 379,476 468,476 468,440",
        "baseline": null,
        "text": ""
    },
    {
        "coords": "468,440 468,476 556,476 556,440",
        "baseline": null,
        "text": ""
    },
    {
        "coords": "556,440 556,476 1024,476 1024,440",
        "baseline": null,
        "text": ""
    },
    {
        "coords": "1024,440 1024,476 1068,476 1068,440",
        "baseline": null,
        "text": ""
    },
    {
        "coords": "1068,440 1068,476 1112,476 1112,440",
        "baseline": null,
        "text": ""
    },
    {
        "coords": "145,476 145,515 194,515 194,476",
        "baseline": null,
        "text": ""
    },
    {
        "coords": "194,476 194,515 287,515 287,476",
        "baseline": null,
        "text": ""
    },
    {
        "coords": "287,476 287,515 325,515 325,476",
        "baseline": null,
        "text": ""
    },
    {
        "coords": "325,476 325,515 379,515 379,476",
        "baseline": null,
        "text": ""
    },
    {
        "coords": "379,476 379,515 468,515 468,476",
        "baseline": null,
        "text": ""
    },
    {
        "coords": "468,476 468,515 556,515 556,476",
        "baseline": null,
        "text": ""
    },
    {
        "coords": "556,476 556,515 1024,515 1024,476",
        "baseline": null,
        "text": ""
    },
    {
        "coords": "1024,476 1024,515 1068,515 1068,476",
        "baseline": null,
        "text": ""
    },
    {
        "coords": "1068,476 1068,515 1112,515 1112,476",
        "baseline": null,
        "text": ""
    },
    {
        "coords": "145,515 145,555 194,555 194,515",
        "baseline": null,
        "text": ""
    },
    {
        "coords": "194,515 194,555 287,555 287,515",
        "baseline": null,
        "text": ""
    },
    {
        "coords": "287,515 287,555 325,555 325,515",
        "baseline": null,
        "text": ""
    },
    {
        "coords": "325,515 325,555 379,555 379,515",
        "baseline": null,
        "text": ""
    },
    {
        "coords": "379,515 379,555 468,555 468,515",
        "baseline": null,
        "text": ""
    },
    {
        "coords": "468,515 468,555 556,555 556,515",
        "baseline": null,
        "text": ""
    },
    {
        "coords": "556,515 556,555 1024,555 1024,515",
        "baseline": null,
        "text": ""
    },
    {
        "coords": "1024,515 1024,555 1068,555 1068,515",
        "baseline": null,
        "text": ""
    },
    {
        "coords": "1068,515 1068,555 1112,555 1112,515",
        "baseline": null,
        "text": ""
    },
    {
        "coords": "145,555 145,603 194,603 194,555",
        "baseline": null,
        "text": ""
    },
    {
        "coords": "194,555 194,603 287,603 287,555",
        "baseline": null,
        "text": ""
    },
    {
        "coords": "287,555 287,603 325,603 325,555",
        "baseline": null,
        "text": ""
    },
    {
        "coords": "325,555 325,603 379,603 379,555",
        "baseline": null,
        "text": ""
    },
    {
        "coords": "379,555 379,603 468,603 468,555",
        "baseline": null,
        "text": ""
    },
    {
        "coords": "468,555 468,603 556,603 556,555",
        "baseline": null,
        "text": ""
    },
    {
        "coords": "556,555 556,603 1024,603 1024,555",
        "baseline": null,
        "text": ""
    },
    {
        "coords": "1024,555 1024,603 1068,603 1068,555",
        "baseline": null,
        "text": ""
    },
    {
        "coords": "1068,555 1068,603 1112,603 1112,555",
        "baseline": null,
        "text": ""
    },
    {
        "coords": "145,603 145,641 194,641 194,603",
        "baseline": null,
        "text": ""
    },
    {
        "coords": "194,603 194,641 287,641 287,603",
        "baseline": null,
        "text": ""
    },
    {
        "coords": "287,603 287,641 325,641 325,603",
        "baseline": null,
        "text": ""
    },
    {
        "coords": "325,603 325,641 379,641 379,603",
        "baseline": null,
        "text": ""
    },
    {
        "coords": "379,603 379,641 468,641 468,603",
        "baseline": null,
        "text": ""
    },
    {
        "coords": "468,603 468,641 556,641 556,603",
        "baseline": null,
        "text": ""
    },
    {
        "coords": "556,603 556,641 1024,641 1024,603",
        "baseline": null,
        "text": ""
    },
    {
        "coords": "1024,603 1024,641 1068,641 1068,603",
        "baseline": null,
        "text": ""
    },
    {
        "coords": "1068,603 1068,641 1112,641 1112,603",
        "baseline": null,
        "text": ""
    },
    {
        "coords": "145,641 145,678 194,678 194,641",
        "baseline": null,
        "text": ""
    },
    {
        "coords": "194,641 194,678 287,678 287,641",
        "baseline": null,
        "text": ""
    },
    {
        "coords": "287,641 287,678 325,678 325,641",
        "baseline": null,
        "text": ""
    },
    {
        "coords": "325,641 325,678 379,678 379,641",
        "baseline": null,
        "text": ""
    },
    {
        "coords": "379,641 379,678 468,678 468,641",
        "baseline": null,
        "text": ""
    },
    {
        "coords": "468,641 468,678 556,678 556,641",
        "baseline": null,
        "text": ""
    },
    {
        "coords": "556,641 556,678 1024,678 1024,641",
        "baseline": null,
        "text": ""
    },
    {
        "coords": "1024,641 1024,678 1068,678 1068,641",
        "baseline": null,
        "text": ""
    },
    {
        "coords": "1068,641 1068,678 1112,678 1112,641",
        "baseline": null,
        "text": ""
    },
    {
        "coords": "145,678 145,723 194,723 194,678",
        "baseline": null,
        "text": ""
    },
    {
        "coords": "194,678 194,723 287,723 287,678",
        "baseline": null,
        "text": ""
    },
    {
        "coords": "287,678 287,723 325,723 325,678",
        "baseline": null,
        "text": ""
    },
    {
        "coords": "325,678 325,723 379,723 379,678",
        "baseline": null,
        "text": ""
    },
    {
        "coords": "379,678 379,723 468,723 468,678",
        "baseline": null,
        "text": ""
    },
    {
        "coords": "468,678 468,723 556,723 556,678",
        "baseline": null,
        "text": ""
    },
    {
        "coords": "556,678 556,723 1024,723 1024,678",
        "baseline": null,
        "text": ""
    },
    {
        "coords": "1024,678 1024,723 1068,723 1068,678",
        "baseline": null,
        "text": ""
    },
    {
        "coords": "1068,678 1068,723 1112,723 1112,678",
        "baseline": null,
        "text": ""
    },
    {
        "coords": "145,723 145,764 194,764 194,723",
        "baseline": null,
        "text": ""
    },
    {
        "coords": "194,723 194,764 287,764 287,723",
        "baseline": null,
        "text": ""
    },
    {
        "coords": "287,723 287,764 325,764 325,723",
        "baseline": null,
        "text": ""
    },
    {
        "coords": "325,723 325,764 379,764 379,723",
        "baseline": null,
        "text": ""
    },
    {
        "coords": "379,723 379,764 468,764 468,723",
        "baseline": null,
        "text": ""
    },
    {
        "coords": "468,723 468,764 556,764 556,723",
        "baseline": null,
        "text": ""
    },
    {
        "coords": "556,723 556,764 1024,764 1024,723",
        "baseline": null,
        "text": ""
    },
    {
        "coords": "1024,723 1024,764 1068,764 1068,723",
        "baseline": null,
        "text": ""
    },
    {
        "coords": "1068,723 1068,764 1112,764 1112,723",
        "baseline": null,
        "text": ""
    },
    {
        "coords": "145,764 145,841 194,841 194,764",
        "baseline": null,
        "text": ""
    },
    {
        "coords": "194,764 194,841 287,841 287,764",
        "baseline": null,
        "text": ""
    },
    {
        "coords": "287,764 287,841 325,841 325,764",
        "baseline": null,
        "text": ""
    },
    {
        "coords": "325,764 325,841 379,841 379,764",
        "baseline": null,
        "text": ""
    },
    {
        "coords": "379,764 379,841 468,841 468,764",
        "baseline": null,
        "text": ""
    },
    {
        "coords": "468,764 468,841 556,841 556,764",
        "baseline": null,
        "text": ""
    },
    {
        "coords": "556,764 556,841 1024,841 1024,764",
        "baseline": null,
        "text": ""
    },
    {
        "coords": "1024,764 1024,841 1068,841 1068,764",
        "baseline": null,
        "text": ""
    },
    {
        "coords": "1068,764 1068,841 1112,841 1112,764",
        "baseline": null,
        "text": ""
    },
    {
        "coords": "145,841 145,924 194,924 194,841",
        "baseline": null,
        "text": ""
    },
    {
        "coords": "194,841 194,924 287,924 287,841",
        "baseline": null,
        "text": ""
    },
    {
        "coords": "287,841 287,924 325,924 325,841",
        "baseline": null,
        "text": ""
    },
    {
        "coords": "325,841 325,924 379,924 379,841",
        "baseline": null,
        "text": ""
    },
    {
        "coords": "379,841 379,924 468,924 468,841",
        "baseline": null,
        "text": ""
    },
    {
        "coords": "468,841 468,924 556,924 556,841",
        "baseline": null,
        "text": ""
    },
    {
        "coords": "556,841 556,924 1024,924 1024,841",
        "baseline": null,
        "text": ""
    },
    {
        "coords": "1024,841 1024,924 1068,924 1068,841",
        "baseline": null,
        "text": ""
    },
    {
        "coords": "1068,841 1068,924 1112,924 1112,841",
        "baseline": null,
        "text": ""
    },
    {
        "coords": "145,924 145,965 194,965 194,924",
        "baseline": null,
        "text": ""
    },
    {
        "coords": "194,924 194,965 287,965 287,924",
        "baseline": null,
        "text": ""
    },
    {
        "coords": "287,924 287,965 325,965 325,924",
        "baseline": null,
        "text": ""
    },
    {
        "coords": "325,924 325,965 379,965 379,924",
        "baseline": null,
        "text": ""
    },
    {
        "coords": "379,924 379,965 468,965 468,924",
        "baseline": null,
        "text": ""
    },
    {
        "coords": "468,924 468,965 556,965 556,924",
        "baseline": null,
        "text": ""
    },
    {
        "coords": "556,924 556,965 1024,965 1024,924",
        "baseline": null,
        "text": ""
    },
    {
        "coords": "1024,924 1024,965 1068,965 1068,924",
        "baseline": null,
        "text": ""
    },
    {
        "coords": "1068,924 1068,965 1112,965 1112,924",
        "baseline": null,
        "text": ""
    },
    {
        "coords": "145,965 145,1045 194,1045 194,965",
        "baseline": null,
        "text": ""
    },
    {
        "coords": "194,965 194,1045 287,1045 287,965",
        "baseline": null,
        "text": ""
    },
    {
        "coords": "287,965 287,1045 325,1045 325,965",
        "baseline": null,
        "text": ""
    },
    {
        "coords": "325,965 325,1045 379,1045 379,965",
        "baseline": null,
        "text": ""
    },
    {
        "coords": "379,965 379,1045 468,1045 468,965",
        "baseline": null,
        "text": ""
    },
    {
        "coords": "468,965 468,1045 556,1045 556,965",
        "baseline": null,
        "text": ""
    },
    {
        "coords": "556,965 556,1045 1024,1045 1024,965",
        "baseline": null,
        "text": ""
    },
    {
        "coords": "1024,965 1024,1045 1068,1045 1068,965",
        "baseline": null,
        "text": ""
    },
    {
        "coords": "1068,965 1068,1045 1112,1045 1112,965",
        "baseline": null,
        "text": ""
    },
    {
        "coords": "145,1045 145,1132 194,1132 194,1045",
        "baseline": null,
        "text": ""
    },
    {
        "coords": "194,1045 194,1132 287,1132 287,1045",
        "baseline": null,
        "text": ""
    },
    {
        "coords": "287,1045 287,1132 325,1132 325,1045",
        "baseline": null,
        "text": ""
    },
    {
        "coords": "325,1045 325,1132 379,1132 379,1045",
        "baseline": null,
        "text": ""
    },
    {
        "coords": "379,1045 379,1132 468,1132 468,1045",
        "baseline": null,
        "text": ""
    },
    {
        "coords": "468,1045 468,1132 556,1132 556,1045",
        "baseline": null,
        "text": ""
    },
    {
        "coords": "556,1045 556,1132 1024,1132 1024,1045",
        "baseline": null,
        "text": ""
    },
    {
        "coords": "1024,1045 1024,1132 1068,1132 1068,1045",
        "baseline": null,
        "text": ""
    },
    {
        "coords": "1068,1045 1068,1132 1112,1132 1112,1045",
        "baseline": null,
        "text": ""
    },
    {
        "coords": "145,1132 145,1176 194,1176 194,1132",
        "baseline": null,
        "text": ""
    },
    {
        "coords": "194,1132 194,1176 287,1176 287,1132",
        "baseline": null,
        "text": ""
    },
    {
        "coords": "287,1132 287,1176 325,1176 325,1132",
        "baseline": null,
        "text": ""
    },
    {
        "coords": "325,1132 325,1176 379,1176 379,1132",
        "baseline": null,
        "text": ""
    },
    {
        "coords": "379,1132 379,1176 468,1176 468,1132",
        "baseline": null,
        "text": ""
    },
    {
        "coords": "468,1132 468,1176 556,1176 556,1132",
        "baseline": null,
        "text": ""
    },
    {
        "coords": "556,1132 556,1176 1024,1176 1024,1132",
        "baseline": null,
        "text": ""
    },
    {
        "coords": "1024,1132 1024,1176 1068,1176 1068,1132",
        "baseline": null,
        "text": ""
    },
    {
        "coords": "1068,1132 1068,1176 1112,1176 1112,1132",
        "baseline": null,
        "text": ""
    },
    {
        "coords": "145,1176 145,1215 194,1215 194,1176",
        "baseline": null,
        "text": ""
    },
    {
        "coords": "194,1176 194,1215 287,1215 287,1176",
        "baseline": null,
        "text": ""
    },
    {
        "coords": "287,1176 287,1215 325,1215 325,1176",
        "baseline": null,
        "text": ""
    },
    {
        "coords": "325,1176 325,1215 379,1215 379,1176",
        "baseline": null,
        "text": ""
    },
    {
        "coords": "379,1176 379,1215 468,1215 468,1176",
        "baseline": null,
        "text": ""
    },
    {
        "coords": "468,1176 468,1215 556,1215 556,1176",
        "baseline": null,
        "text": ""
    },
    {
        "coords": "556,1176 556,1215 1024,1215 1024,1176",
        "baseline": null,
        "text": ""
    },
    {
        "coords": "1024,1176 1024,1215 1068,1215 1068,1176",
        "baseline": null,
        "text": ""
    },
    {
        "coords": "1068,1176 1068,1215 1112,1215 1112,1176",
        "baseline": null,
        "text": ""
    },
    {
        "coords": "145,1215 145,1257 194,1257 194,1215",
        "baseline": null,
        "text": ""
    },
    {
        "coords": "194,1215 194,1257 287,1257 287,1215",
        "baseline": null,
        "text": ""
    },
    {
        "coords": "287,1215 287,1257 325,1257 325,1215",
        "baseline": null,
        "text": ""
    },
    {
        "coords": "325,1215 325,1257 379,1257 379,1215",
        "baseline": null,
        "text": ""
    },
    {
        "coords": "379,1215 379,1257 468,1257 468,1215",
        "baseline": null,
        "text": ""
    },
    {
        "coords": "468,1215 468,1257 556,1257 556,1215",
        "baseline": null,
        "text": ""
    },
    {
        "coords": "556,1215 556,1257 1024,1257 1024,1215",
        "baseline": null,
        "text": ""
    },
    {
        "coords": "1024,1215 1024,1257 1068,1257 1068,1215",
        "baseline": null,
        "text": ""
    },
    {
        "coords": "1068,1215 1068,1257 1112,1257 1112,1215",
        "baseline": null,
        "text": ""
    },
    {
        "coords": "145,1257 145,1301 194,1301 194,1257",
        "baseline": null,
        "text": ""
    },
    {
        "coords": "194,1257 194,1301 287,1301 287,1257",
        "baseline": null,
        "text": ""
    },
    {
        "coords": "287,1257 287,1301 325,1301 325,1257",
        "baseline": null,
        "text": ""
    },
    {
        "coords": "325,1257 325,1301 379,1301 379,1257",
        "baseline": null,
        "text": ""
    },
    {
        "coords": "379,1257 379,1301 468,1301 468,1257",
        "baseline": null,
        "text": ""
    },
    {
        "coords": "468,1257 468,1301 556,1301 556,1257",
        "baseline": null,
        "text": ""
    },
    {
        "coords": "556,1257 556,1301 1024,1301 1024,1257",
        "baseline": null,
        "text": ""
    },
    {
        "coords": "1024,1257 1024,1301 1068,1301 1068,1257",
        "baseline": null,
        "text": ""
    },
    {
        "coords": "1068,1257 1068,1301 1112,1301 1112,1257",
        "baseline": null,
        "text": ""
    },
    {
        "coords": "145,1301 145,1336 194,1336 194,1301",
        "baseline": null,
        "text": ""
    },
    {
        "coords": "194,1301 194,1336 287,1336 287,1301",
        "baseline": null,
        "text": ""
    },
    {
        "coords": "287,1301 287,1336 325,1336 325,1301",
        "baseline": null,
        "text": ""
    },
    {
        "coords": "325,1301 325,1336 379,1336 379,1301",
        "baseline": null,
        "text": ""
    },
    {
        "coords": "379,1301 379,1336 468,1336 468,1301",
        "baseline": null,
        "text": ""
    },
    {
        "coords": "468,1301 468,1336 556,1336 556,1301",
        "baseline": null,
        "text": ""
    },
    {
        "coords": "556,1301 556,1336 1024,1336 1024,1301",
        "baseline": null,
        "text": ""
    },
    {
        "coords": "1024,1301 1024,1336 1068,1336 1068,1301",
        "baseline": null,
        "text": ""
    },
    {
        "coords": "1068,1301 1068,1336 1112,1336 1112,1301",
        "baseline": null,
        "text": ""
    },
    {
        "coords": "145,1336 145,1380 194,1380 194,1336",
        "baseline": null,
        "text": ""
    },
    {
        "coords": "194,1336 194,1380 287,1380 287,1336",
        "baseline": null,
        "text": ""
    },
    {
        "coords": "287,1336 287,1380 325,1380 325,1336",
        "baseline": null,
        "text": ""
    },
    {
        "coords": "325,1336 325,1380 379,1380 379,1336",
        "baseline": null,
        "text": ""
    },
    {
        "coords": "379,1336 379,1380 468,1380 468,1336",
        "baseline": null,
        "text": ""
    },
    {
        "coords": "468,1336 468,1380 556,1380 556,1336",
        "baseline": null,
        "text": ""
    },
    {
        "coords": "556,1336 556,1380 1024,1380 1024,1336",
        "baseline": null,
        "text": ""
    },
    {
        "coords": "1024,1336 1024,1380 1068,1380 1068,1336",
        "baseline": null,
        "text": ""
    },
    {
        "coords": "1068,1336 1068,1380 1112,1380 1112,1336",
        "baseline": null,
        "text": ""
    },
    {
        "coords": "145,1380 145,1422 194,1422 194,1380",
        "baseline": null,
        "text": ""
    },
    {
        "coords": "194,1380 194,1422 287,1422 287,1380",
        "baseline": null,
        "text": ""
    },
    {
        "coords": "287,1380 287,1422 325,1422 325,1380",
        "baseline": null,
        "text": ""
    },
    {
        "coords": "325,1380 325,1422 379,1422 379,1380",
        "baseline": null,
        "text": ""
    },
    {
        "coords": "379,1380 379,1422 468,1422 468,1380",
        "baseline": null,
        "text": ""
    },
    {
        "coords": "468,1380 468,1422 556,1422 556,1380",
        "baseline": null,
        "text": ""
    },
    {
        "coords": "556,1380 556,1422 1024,1422 1024,1380",
        "baseline": null,
        "text": ""
    },
    {
        "coords": "1024,1380 1024,1422 1068,1422 1068,1380",
        "baseline": null,
        "text": ""
    },
    {
        "coords": "1068,1380 1068,1422 1112,1422 1112,1380",
        "baseline": null,
        "text": ""
    },
    {
        "coords": "145,1422 146,1465 194,1465 194,1422",
        "baseline": null,
        "text": ""
    },
    {
        "coords": "194,1422 194,1465 287,1465 287,1422",
        "baseline": null,
        "text": ""
    },
    {
        "coords": "287,1422 287,1465 325,1465 325,1422",
        "baseline": null,
        "text": ""
    },
    {
        "coords": "325,1422 325,1465 379,1465 379,1422",
        "baseline": null,
        "text": ""
    },
    {
        "coords": "379,1422 379,1465 468,1465 468,1422",
        "baseline": null,
        "text": ""
    },
    {
        "coords": "468,1422 468,1465 556,1465 556,1422",
        "baseline": null,
        "text": ""
    },
    {
        "coords": "556,1422 556,1465 1024,1465 1024,1422",
        "baseline": null,
        "text": ""
    },
    {
        "coords": "1024,1422 1024,1465 1068,1465 1068,1422",
        "baseline": null,
        "text": ""
    },
    {
        "coords": "1068,1422 1068,1465 1112,1465 1112,1422",
        "baseline": null,
        "text": ""
    },
    {
        "coords": "146,1465 147,1510 194,1510 194,1465",
        "baseline": null,
        "text": ""
    },
    {
        "coords": "194,1465 194,1510 287,1510 287,1465",
        "baseline": null,
        "text": ""
    },
    {
        "coords": "287,1465 287,1510 325,1510 325,1465",
        "baseline": null,
        "text": ""
    },
    {
        "coords": "325,1465 325,1510 379,1510 379,1465",
        "baseline": null,
        "text": ""
    },
    {
        "coords": "379,1465 379,1510 468,1510 468,1465",
        "baseline": null,
        "text": ""
    },
    {
        "coords": "468,1465 468,1510 556,1510 556,1465",
        "baseline": null,
        "text": ""
    },
    {
        "coords": "556,1465 556,1510 1024,1510 1024,1465",
        "baseline": null,
        "text": ""
    },
    {
        "coords": "1024,1465 1024,1510 1068,1510 1068,1465",
        "baseline": null,
        "text": ""
    },
    {
        "coords": "1068,1465 1068,1510 1112,1510 1112,1465",
        "baseline": null,
        "text": ""
    },
    {
        "coords": "147,1510 148,1587 194,1587 194,1510",
        "baseline": null,
        "text": ""
    },
    {
        "coords": "194,1510 194,1587 287,1587 287,1510",
        "baseline": null,
        "text": ""
    },
    {
        "coords": "287,1510 287,1587 325,1587 325,1510",
        "baseline": null,
        "text": ""
    },
    {
        "coords": "325,1510 325,1587 379,1587 379,1510",
        "baseline": null,
        "text": ""
    },
    {
        "coords": "379,1510 379,1587 468,1587 468,1510",
        "baseline": null,
        "text": ""
    },
    {
        "coords": "468,1510 468,1587 556,1587 556,1510",
        "baseline": null,
        "text": ""
    },
    {
        "coords": "556,1510 556,1587 1024,1587 1024,1510",
        "baseline": null,
        "text": ""
    },
    {
        "coords": "1024,1510 1024,1587 1068,1587 1068,1510",
        "baseline": null,
        "text": ""
    },
    {
        "coords": "1068,1510 1068,1587 1112,1587 1112,1510",
        "baseline": null,
        "text": ""
    },
    {
        "coords": "148,1587 148,1635 194,1635 194,1587",
        "baseline": null,
        "text": ""
    },
    {
        "coords": "194,1587 194,1635 287,1635 287,1587",
        "baseline": null,
        "text": ""
    },
    {
        "coords": "287,1587 287,1635 325,1635 325,1587",
        "baseline": null,
        "text": ""
    },
    {
        "coords": "325,1587 325,1635 379,1635 379,1587",
        "baseline": null,
        "text": ""
    },
    {
        "coords": "379,1587 379,1635 468,1635 468,1587",
        "baseline": null,
        "text": ""
    },
    {
        "coords": "468,1587 468,1635 556,1635 556,1587",
        "baseline": null,
        "text": ""
    },
    {
        "coords": "556,1587 556,1635 1024,1637 1024,1587",
        "baseline": null,
        "text": ""
    },
    {
        "coords": "1024,1587 1024,1637 1068,1637 1068,1587",
        "baseline": null,
        "text": ""
    },
    {
        "coords": "1068,1587 1068,1637 1112,1637 1112,1587",
        "baseline": null,
        "text": ""
    }
]